pyFM/__init__.py
pyFM/functional.py
pyFM/FMN/FMN.py
pyFM/FMN/__init__.py
pyFM/eval/__init__.py
pyFM/eval/evaluate.py
pyFM/mesh/__init__.py
pyFM/mesh/file_utils.py
pyFM/mesh/geometry.py
pyFM/mesh/laplacian.py
pyFM/mesh/trimesh.py
pyFM/optimize/__init__.py
pyFM/optimize/base_functions.py
pyFM/refine/__init__.py
pyFM/refine/icp.py
pyFM/refine/zoomout.py
pyFM/signatures/HKS_functions.py
pyFM/signatures/WKS_functions.py
pyFM/signatures/__init__.py
pyFM/spectral/__init__.py
pyFM/spectral/convert.py
pyFM/spectral/nn_utils.py
pyFM/spectral/projection_utils.py
pyFM/spectral/shape_difference.py
pyfmaps-1.0.1.dist-info/LICENSE
pyfmaps-1.0.1.dist-info/METADATA
pyfmaps-1.0.1.dist-info/WHEEL
pyfmaps-1.0.1.dist-info/top_level.txt
pyfmaps-1.0.1.dist-info/RECORD
