Metadata-Version: 2.2
Name: pyfmaps
Version: 1.0.1
Summary: Python bindings for functional maps
Author: Robin Magnet
License: MIT License
Project-URL: Bug Tracker, https://github.com/RobinMagnet/pyFM/issues
Project-URL: Documentation, https://github.com/RobinMagnet/pyFM/blob/master/example_notebook.ipynb
Project-URL: Source Code, https://github.com/RobinMagnet/pyFM
Project-URL: User Support, https://github.com/RobinMagnet/pyFM/issues
Classifier: Development Status :: 2 - Pre-Alpha
Classifier: Intended Audience :: Developers
Classifier: License :: OSI Approved :: MIT License
Classifier: Operating System :: OS Independent
Classifier: Programming Language :: Python
Classifier: Programming Language :: Python :: 3
Classifier: Programming Language :: Python :: 3 :: Only
Classifier: Programming Language :: Python :: 3.7
Classifier: Programming Language :: Python :: 3.8
Classifier: Programming Language :: Python :: 3.9
Classifier: Programming Language :: Python :: 3.10
Classifier: Topic :: Software Development :: Testing
Requires-Python: >=3.7
License-File: LICENSE
Requires-Dist: numpy
Requires-Dist: scipy
Requires-Dist: potpourri3d
Requires-Dist: robust_laplacian
Requires-Dist: tqdm
Requires-Dist: scikit-learn
